{
  "size": 10,
  "from": {{multiply (subtract (default @root.request.params.query.page 1) 1) 10}},
  "_source": [
    "categories",
    "categories_id",
    "categories_slug",
    "post_tags",
    "post_tags_slug",
    "post_tags_id",
    "title",
    "path",
    "url",
    "author_avatar",
    "og_image",
    "author_slug",
    "author_name_full",
    "publish_on",
    "updated"
  ],
  "query": {
    "bool": {
      "must_not": [
        {
          "term": {
            "hide_in_results": true
          }
        },
        {
          "term": {
            "hide_from_search": "1"
          }
        },
        {
          "term": {
            "is_press_release": true
          }
        }
      ],
      "must": [
        {
          "term": {
            "post_tags_slug": "consultation-response"
          }
        }
      ]
    }
  },
  "sort": {
    "publish_on": "desc"
  }
}
