{
  "defaults": {
    {{#ifAny @root.request.params.charity_number @root.data.application_data.request.data.data_object.get_grant.records.[0] ~}}
    {{#withExtend this application=@root.data.application_data.request.data.data_object.get_grant.records.[0] oscr=@root.data.oscr_data.hits.hits.[0]._source milo=@root.data.milo_data.hits.hits.[0]._source postcode=@root.data.postcode_data.[0]}}
    "application_editing": {{{json value=(default application.Id "")}}},
    "application_readonly": {{#if (contains @root.route.name "fund_kirk_view_form")}}true{{else}}false{{/if}},
    "application_call": {{{json value=(default application.Call__c "")}}},
    "application_status": {{{json value=(default application.Application_Satus__c "")}}},
    "is_charity": {{{json value=(default (default application.Charity_Number__c oscr.charity_number) "")}}},
    "tfa_21": {{{json value=(default oscr.charity_number "")}}},
    "tfa_20": {{{json value=(default oscr.constitutional_form "")}}},
    "tfa_3": {{{json value=(default oscr.charity_name "")}}},
    "tfa_6": {{{json value=(default milo.location_street "")}}},
    "tfa_7": {{{json value=(default (default milo.location_city milo.location_region) "")}}},
    "tfa_x": {{{json value=(default postcode.local_authority "")}}},
    "tfa_8": {{{json value=(default (default oscr.postcode postcode.place) "")}}},
    "tfa_9": {{{json value=(default (if (contains 'http' oscr.website) oscr.website) "")}}},
    "tfa_10": {{{json value=(default (if (contains 'http' milo.twitter) milo.twitter) "")}}},
    "tfa_11": {{{json value=(default (if (contains 'http' milo.facebook) milo.facebook) "")}}}
    {{/withExtend}}
    {{/ifAny}}
  }
}